spotify_dl.py
ez_spotify_dl-1.3.1.dist-info/METADATA
ez_spotify_dl-1.3.1.dist-info/RECORD
ez_spotify_dl-1.3.1.dist-info/WHEEL
ez_spotify_dl-1.3.1.dist-info/entry_points.txt
ez_spotify_dl-1.3.1.dist-info/top_level.txt
