Metadata-Version: 2.1
Name: ez-spotify-dl
Version: 1.3.1
Summary: Spotify downloader tool
Home-page: https://bitbucket.org/sacanix/spotify_dl
Author: Tony Kamillo
Author-email: tonysacanix@gmail.com
License: GPL
Keywords: spotify download tool
Platform: UNKNOWN
Requires-Dist: awesome-slugify (==1.6.5)
Requires-Dist: backports.shutil-get-terminal-size (==1.0.0)
Requires-Dist: beautifulsoup4 (==4.6.1)
Requires-Dist: certifi (==2018.4.16)
Requires-Dist: chardet (==3.0.4)
Requires-Dist: click (==6.7)
Requires-Dist: decorator (==4.3.0)
Requires-Dist: enum34 (==1.1.6)
Requires-Dist: eyeD3 (==0.8.7)
Requires-Dist: Flask (==1.0.2)
Requires-Dist: idna (==2.7)
Requires-Dist: instantmusic (==2.2)
Requires-Dist: ipython (==5.8.0)
Requires-Dist: ipython-genutils (==0.2.0)
Requires-Dist: itsdangerous (==0.24)
Requires-Dist: Jinja2 (==2.10)
Requires-Dist: MarkupSafe (==1.0)
Requires-Dist: pathlib (==1.0.1)
Requires-Dist: pathlib2 (==2.3.2)
Requires-Dist: pexpect (==4.6.0)
Requires-Dist: pickleshare (==0.7.4)
Requires-Dist: prompt-toolkit (==1.0.15)
Requires-Dist: ptyprocess (==0.6.0)
Requires-Dist: Pygments (==2.2.0)
Requires-Dist: python-magic (==0.4.15)
Requires-Dist: regex (==2018.7.11)
Requires-Dist: requests (==2.19.1)
Requires-Dist: scandir (==1.8)
Requires-Dist: simplegeneric (==0.8.1)
Requires-Dist: six (==1.11.0)
Requires-Dist: traitlets (==4.3.2)
Requires-Dist: Unidecode (==1.0.22)
Requires-Dist: urllib3 (==1.23)
Requires-Dist: wcwidth (==0.1.7)
Requires-Dist: Werkzeug (==0.14.1)
Requires-Dist: youtube-dl (==2018.9.10)
